gundam-0.0.2.dist-info/RECORD
gundam-0.0.2.dist-info/WHEEL
gundam-0.0.2.dist-info/METADATA
gundam-0.0.2.dist-info/licenses/LICENSE
gundam/_version.py
gundam/cflibfor.pyf
gundam/__init__.py
gundam/cflibfor.f90
gundam/gundam.py
gundam/cflibfor.cpython-39-darwin.so
gundam/.dylibs/libgfortran.5.dylib
gundam/.dylibs/libquadmath.0.dylib
gundam/.dylibs/libgcc_s.1.1.dylib
gundam/.dylibs/libgomp.1.dylib
