Metadata-Version: 2.1
Name: gundam
Version: 0.0.2
Author-Email: Emilio Donoso <edonoso@conicet.gov.ar>
License: MIT License
Classifier: Development Status :: 4 - Beta
Classifier: Intended Audience :: Developers
Classifier: Intended Audience :: Science/Research
Classifier: Operating System :: OS Independent
Classifier: Programming Language :: Python
Project-URL: Source code, https://github.com/lincc-frameworks-mask-incubator/gundam
Requires-Python: <3.12,>=3.9
Requires-Dist: numpy
Requires-Dist: matplotlib
Requires-Dist: astropy
Requires-Dist: scipy
Requires-Dist: munch
Requires-Dist: pymorton
Requires-Dist: jupyter; extra == "dev"
Requires-Dist: pre-commit; extra == "dev"
Requires-Dist: pytest; extra == "dev"
Requires-Dist: pytest-cov; extra == "dev"
Requires-Dist: ruff; extra == "dev"
Provides-Extra: dev
